nobus/__init__.py
nobus/managed.py
nobus/randname.py
nobus/safeattr.py
nobus/typecheck.py
nobus/utils.py
nobus-0.1.7.dist-info/LICENSE
nobus-0.1.7.dist-info/METADATA
nobus-0.1.7.dist-info/WHEEL
nobus-0.1.7.dist-info/RECORD
