Metadata-Version: 2.1
Name: nobus
Version: 0.1.7
Summary: 
License: MIT
Author: Josh Nobus
Requires-Python: >=3.11,<4.0
Classifier: License :: OSI Approved :: MIT License
Classifier: Programming Language :: Python :: 3
Classifier: Programming Language :: Python :: 3.11
Classifier: Programming Language :: Python :: 3.12
Requires-Dist: requests (>=2.28.2,<3.0.0,!=2.30.0)
Requires-Dist: tqdm (>=4.66.2,<5.0.0)
